[
  {
    "alert_type": "Transaction Anomaly",
    "severity": "MEDIUM",
    "action_recommendation": "**Transaction Analysis and Risk Assessment**\n\nBased on the provided transaction data and regulatory context, I will analyze the transaction for potential compliance risks and recommend necessary actions for risk mitigation.\n\n**1. Transaction Fields and Relevance to AML/KYC Compliance**\n\n* `customerId`: CUST123 - This field is relevant to identifying the customer and verifying their identity.\n* `amount`: 35,000 INR - This field is relevant to monitoring large or unusual transactions.\n* `frequency30Day`: 45 - This field is relevant to identifying patterns such as rapid movement of funds.\n* `customerAvgAmount`: 18,000 INR - This field is relevant to identifying deviations from customer profiles.\n* `customerTotalTransactions`: 60 - This field is relevant to identifying patterns such as frequent transactions.\n* `geographicDistance`: 1,150 km - This field is relevant to monitoring transactions involving offshore financial centers or high-risk countries.\n* `cityDistance`: 1,400 km - This field is relevant to monitoring transactions involving high-risk jurisdictions.\n* `transactionType`: Cash Deposit - This field is relevant to monitoring unusual transaction patterns.\n* `unusualForCustomer`: No - This field is relevant to identifying deviations from customer profiles.\n* `customerRiskProfile`: Medium - This field is relevant to assessing customer-specific risk factors.\n* `transactionPurpose`: Loan Repayment - This field is relevant to identifying the economic or lawful purpose of the transaction.\n* `historicalRiskScore`: 72.5 - This field is relevant to assessing customer-specific risk factors.\n* `customerIndustry`: Finance - This field is relevant to identifying high-risk industries.\n* `originCountry`: India - This field is relevant to monitoring transactions involving high-risk countries.\n* `destinationCountry`: India - This field is relevant to monitoring transactions involving high-risk countries.\n* `originCity`: Mumbai - This field is relevant to monitoring transactions involving high-risk jurisdictions.\n* `destinationCity`: Delhi - This field is relevant to monitoring transactions involving high-risk jurisdictions.\n* `customerType`: Individual - This field is relevant to identifying individual customers and assessing their risk profile.\n\n**2. Potential Compliance Risks**\n\n* High-risk jurisdiction: Both the origin and destination countries are India, which is not typically considered a high-risk country.\n* Unusual transaction pattern: The transaction amount is slightly higher than the customer's average transaction amount, but not significantly so.\n* Deviation from customer profile: The transaction amount is higher than the customer's average transaction amount, but the customer's risk profile is medium, indicating a moderate level of risk.\n* No apparent economic or lawful purpose: The transaction purpose is loan repayment, which appears to be legitimate.\n\n**3. Anomaly Detection Flags**\n\n* Velocity: The transaction frequency is moderate, but not unusually high.\n* Round-number transactions: The transaction amount is not a round number, but the customer's average transaction amount is.\n* Repeated transfers: There is no indication of repeated transfers.\n\n**4. Recommended Actions**\n\n* No enhanced due diligence is required at this time, as the transaction appears to be legitimate.\n* No SAR filing is required at this time, as the transaction does not indicate suspicious activity.\n* Monitor the customer's transactions and risk profile to ensure that they continue to operate within expected boundaries.\n\n**5. Severity of Potential Violations**\n\n* Low: The transaction does not indicate a high level of risk or suspicious activity.\n\n**6. Regulatory Concerns**\n\n* No regulatory concerns are identified at this time, as the transaction appears to be legitimate.\n\n**7. Escalation or Further Investigation**\n\n* No escalation or further investigation is required at this time, as the transaction appears to be legitimate.\n\nIn conclusion, the transaction appears to be legitimate and does not indicate a high level of risk or suspicious activity. However, it is important to continue monitoring the customer's transactions and risk profile to ensure that they continue to operate within expected boundaries.",
    "transaction_details": {
      "customerId": "CUST123",
      "amount": 35000,
      "frequency30Day": 45,
      "customerAvgAmount": 18000,
      "customerTotalTransactions": 60,
      "geographicDistance": 1150,
      "cityDistance": 1400,
      "transactionType": "Cash Deposit",
      "unusualForCustomer": "No",
      "customerRiskProfile": "Medium",
      "transactionPurpose": "Loan Repayment",
      "historicalRiskScore": 72.5,
      "customerIndustry": "Finance",
      "originCountry": "India",
      "destinationCountry": "India",
      "originCity": "Mumbai",
      "destinationCity": "Delhi",
      "customerType": "Individual"
    },
    "timestamp": "2025-04-14T10:32:23.806023+00:00"
  },
  {
    "alert_type": "Transaction Anomaly",
    "severity": "HIGH",
    "action_recommendation": "**Transaction Data Analysis for AML/KYC Compliance**\n\n**Overview of Transaction Fields and Relevance to AML/KYC Compliance:**\n\n1. **amount (50,000 INR)**: Large transaction amount, potentially exceeding reporting thresholds.\n2. **frequency30Day (23)**: High frequency of transactions, which may indicate suspicious activity.\n3. **customerAvgAmount (18,000 INR)**: The average transaction amount for this customer is significantly lower than the current transaction, potentially indicating an unusual pattern.\n4. **customerTotalTransactions (75)**: The customer has a large number of transactions, which may indicate a high-risk customer.\n5. **geographicDistance (1,150 km)**: The distance between the origin and destination cities is relatively short, which may indicate a local transaction.\n6. **cityDistance (1,400 km)**: The distance between the origin and destination cities is relatively short, which may indicate a local transaction.\n7. **transactionType (Cash Deposit)**: Cash deposits can be high-risk due to the difficulty in tracing the source of funds.\n8. **unusualForCustomer (Yes)**: This transaction is unusual for the customer, which may indicate suspicious activity.\n9. **customerRiskProfile (Medium)**: The customer has a medium-risk profile, which may indicate a higher level of scrutiny is required.\n10. **transactionPurpose (Loan Repayment)**: The transaction purpose is legitimate, but it's essential to verify the loan details and the customer's identity.\n11. **historicalRiskScore (70.0)**: The customer has a medium-risk score, which may indicate a higher level of scrutiny is required.\n12. **customerIndustry (Finance)**: The customer is in the finance industry, which may indicate a higher level of risk.\n13. **originCountry (India)**: The transaction is domestic, which reduces the risk level.\n14. **destinationCountry (India)**: The transaction is domestic, which reduces the risk level.\n15. **originCity (Delhi)**: The origin city is in India, which reduces the risk level.\n16. **destinationCity (Mumbai)**: The destination city is in India, which reduces the risk level.\n17. **customerType (Individual)**: The customer is an individual, which may indicate a lower level of risk.\n18. **customer_id (CUS125)**: The customer ID is not relevant to AML/KYC compliance.\n\n**Potential Compliance Risks:**\n\n1. **High-risk transaction amount**: The transaction amount is large and may exceed reporting thresholds.\n2. **Unusual transaction pattern**: The transaction is unusual for the customer, which may indicate suspicious activity.\n3. **High-frequency transactions**: The customer has a high frequency of transactions, which may indicate suspicious activity.\n4. **Cash deposit**: Cash deposits can be high-risk due to the difficulty in tracing the source of funds.\n\n**Anomaly Detection Flags:**\n\n1. **High transaction amount**: The transaction amount is significantly higher than the customer's average transaction amount.\n2. **Unusual transaction pattern**: The transaction is unusual for the customer, which may indicate suspicious activity.\n3. **High-frequency transactions**: The customer has a high frequency of transactions, which may indicate suspicious activity.\n\n**Recommendations for Risk Mitigation:**\n\n1. **Enhanced due diligence**: Conduct enhanced due diligence on the customer to verify their identity, financial information, and transaction purpose.\n2. **SAR filing**: File a Suspicious Activity Report (SAR) with the regulatory authorities due to the unusual transaction pattern and high-risk transaction amount.\n3. **Monitoring**: Monitor the customer's transactions closely to detect any suspicious activity.\n4. **Verification**: Verify the loan details and the customer's identity to ensure the transaction purpose is legitimate.\n\n**Severity of Potential Violations:**\n\n1. **HIGH**: The transaction amount is unusually high, and the transaction pattern is unusual for the customer.\n\n**Regulatory Concerns:**\n\n1. **Threshold violations**: The transaction amount may exceed reporting thresholds.\n2. **Suspicious patterns**: The transaction pattern is unusual and may indicate suspicious activity.\n3. **High-risk counterparties**: The customer is in the finance industry, which may indicate a higher level of risk.\n\n**Escalation or Further Investigation:**\n\nThe transaction warrants escalation or further investigation due to the high-risk transaction amount, unusual transaction pattern, and high-frequency transactions.",
    "transaction_details": {
      "amount": 50000.0,
      "frequency30Day": 23,
      "customerAvgAmount": 18000.0,
      "customerTotalTransactions": 75,
      "geographicDistance": 1150.0,
      "cityDistance": 1400.0,
      "transactionType": "Cash Deposit",
      "unusualForCustomer": "Yes",
      "customerRiskProfile": "Medium",
      "transactionPurpose": "Loan Repayment",
      "historicalRiskScore": 70.0,
      "customerIndustry": "Finance",
      "originCountry": "India",
      "destinationCountry": "India",
      "originCity": "Delhi",
      "destinationCity": "Mumbai",
      "customerType": "Individual",
      "customer_id": "CUS125"
    },
    "timestamp": "2025-04-21T12:46:51.593037+00:00"
  },
  {
    "alert_type": "Transaction Anomaly",
    "severity": "HIGH",
    "action_recommendation": "**Transaction Analysis Report**\n\n**Transaction Details:**\n\n* Amount: INR45,000 (INR)\n* Frequency (30-day): 45\n* Customer Average Amount: INR18,000 (INR)\n* Customer Total Transactions: 72\n* Geographic Distance: 1,150 km (between origin and destination countries)\n* City Distance: 1,400 km (between origin and destination cities)\n* Transaction Type: Cash Deposit\n* Unusual for Customer: Yes\n* Customer Risk Profile: Medium\n* Transaction Purpose: Loan Repayment\n* Historical Risk Score: 73.0\n* Customer Industry: Finance\n* Origin Country: India\n* Destination Country: India\n* Origin City: Mumbai\n* Destination City: Delhi\n* Customer Type: Individual\n* Customer ID: CUS456\n\n**Regulatory Considerations:**\n\n* The transaction is subject to AML/KYC regulations, which require monitoring and reporting of suspicious activity.\n* Customer due diligence (CDD) and enhanced due diligence (EDD) may be required for high-risk customers or jurisdictions.\n* Monitoring of large or unusual transactions, especially those involving offshore financial centers, high-risk countries, or PEPs, is necessary.\n\n**Analysis:**\n\n1. **Transaction Fields and Relevance to AML/KYC Compliance:**\n\n* Amount: Large and unusual for the customer, potential indicator of money laundering or structuring.\n* Frequency: High frequency of transactions, potential indicator of smurfing or layering.\n* Geographic Distance: Transactions between countries, potential indicator of international money laundering.\n* City Distance: Transactions between cities, potential indicator of internal money laundering.\n* Transaction Type: Cash deposit, potential indicator of cash-based transactions.\n* Unusual for Customer: Yes, potential indicator of unusual behavior.\n* Customer Risk Profile: Medium, potential indicator of moderate risk.\n* Transaction Purpose: Loan Repayment, potential indicator of legitimate financial activity.\n* Historical Risk Score: 73.0, potential indicator of moderate risk.\n* Customer Industry: Finance, potential indicator of high-risk industry.\n* Origin Country: India, potential indicator of high-risk jurisdiction.\n* Destination Country: India, potential indicator of high-risk jurisdiction.\n* Origin City: Mumbai, potential indicator of high-risk city.\n* Destination City: Delhi, potential indicator of high-risk city.\n* Customer Type: Individual, potential indicator of low-risk customer.\n* Customer ID: CUS456, potential indicator of customer identity.\n\n2. **Potential Compliance Risks:**\n\n* High-risk jurisdictions: India, potential indicator of high-risk jurisdiction.\n* Unusual transaction patterns: Large and frequent transactions, potential indicator of money laundering or structuring.\n* Deviations from customer profiles: Unusual behavior for the customer, potential indicator of unusual activity.\n\n3. **Anomaly Detection Flags:**\n\n* Large and unusual transaction amount.\n* High frequency of transactions.\n* Transactions between countries or cities.\n* Unusual transaction type (cash deposit).\n* Unusual behavior for the customer.\n\n4. **Recommendations:**\n\n* Enhanced due diligence for the customer to verify their identity and financial information.\n* Monitoring of the customer's transactions for potential suspicious activity.\n* Reporting of suspicious activity to regulatory authorities.\n\n5. **Severity of Potential Violations:**\n\n* HIGH: Large and unusual transaction amount, high frequency of transactions, and unusual behavior for the customer.\n\n6. **Regulatory Concerns:**\n\n* Violation of thresholds: Large and unusual transaction amount.\n* Suspicious patterns: High frequency of transactions and unusual behavior for the customer.\n* High-risk counterparties: Financial industry and Indian jurisdiction.\n\n7. **Escalation or Further Investigation:**\n\n* The transaction warrants escalation or further investigation due to the potential indicators of money laundering or structuring.\n\n**Conclusion:**\n\nThe transaction analysis indicates potential compliance risks, including high-risk jurisdictions, unusual transaction patterns, and deviations from customer profiles. The large and unusual transaction amount, high frequency of transactions, and unusual behavior for the customer are potential indicators of money laundering or structuring. Enhanced due diligence and monitoring of the customer's transactions are recommended. The transaction warrants escalation or further investigation due to the potential indicators of suspicious activity.",
    "transaction_details": {
      "amount": 45000.0,
      "frequency30Day": 45,
      "customerAvgAmount": 18000.0,
      "customerTotalTransactions": 72,
      "geographicDistance": 1150.0,
      "cityDistance": 1400.0,
      "transactionType": "Cash Deposit",
      "unusualForCustomer": "Yes",
      "customerRiskProfile": "Medium",
      "transactionPurpose": "Loan Repayment",
      "historicalRiskScore": 73.0,
      "customerIndustry": "Finance",
      "originCountry": "India",
      "destinationCountry": "India",
      "originCity": "Mumbai",
      "destinationCity": "Delhi",
      "customerType": "Individual",
      "customer_id": "CUS456"
    },
    "timestamp": "2025-04-21T13:31:54.863794+00:00"
  },
  {
    "alert_type": "Transaction Anomaly",
    "severity": "HIGH",
    "action_recommendation": "**Transaction Analysis**\n\nThe transaction data provided is for a cash deposit of INR 45,000.0 (forty-five thousand Indian Rupees) made by an individual customer (CUS456) with a medium risk profile. The customer is from Mumbai, India, and the transaction is intended for loan repayment.\n\n**Relevance to AML/KYC Compliance:**\n\n1. **Transaction Amount**: The transaction amount is INR 45,000.0, which is above the average transaction amount for this customer (INR 18,000.0). This may indicate a potential anomaly or unusual activity.\n2. **Frequency**: The transaction frequency is 45 times in the last 30 days, which is higher than usual for this customer. This could be a sign of rapid movement of funds.\n3. **Unusual for Customer**: The transaction is marked as \"unusual\" for this customer, which may indicate that it does not conform to their typical transaction patterns.\n4. **Customer Risk Profile**: The customer has a medium risk profile, which may require enhanced due diligence.\n5. **Transaction Type**: The transaction is a cash deposit, which may require additional scrutiny due to the anonymity associated with cash transactions.\n6. **Origin and Destination**: The transaction originates from Mumbai, India, and is destined for Delhi, India, which are both considered low-risk jurisdictions.\n7. **Customer and Counterparty**: The customer is an individual, and there is no information available on the counterparty.\n\n**Potential Compliance Risks:**\n\n1. **Unusual Transaction Pattern**: The transaction frequency and amount may indicate an unusual activity that requires further investigation.\n2. **High-Risk Customer**: The customer has a medium risk profile, which may require enhanced due diligence.\n3. **Cash Transaction**: The transaction is a cash deposit, which may require additional scrutiny due to the anonymity associated with cash transactions.\n\n**Anomaly Detection Flags:**\n\n1. **Transaction Amount**: The transaction amount is above the average transaction amount for this customer.\n2. **Transaction Frequency**: The transaction frequency is higher than usual for this customer.\n3. **Unusual Transaction Pattern**: The transaction pattern is unusual for this customer.\n\n**Recommendations:**\n\n1. **Enhanced Due Diligence**: Conduct enhanced due diligence on the customer to gather more information about their financial activities and relationships.\n2. **SAR Filing**: File a Suspicious Activity Report (SAR) with the relevant regulatory authorities to report the unusual transaction pattern.\n3. **Customer Interview**: Conduct an interview with the customer to gather more information about the transaction and their financial activities.\n\n**Severity of Potential Violations:**\n\nThe severity of the potential violations is classified as MEDIUM due to the unusual transaction pattern and the customer's medium risk profile.\n\n**Regulatory Concerns:**\n\n1. **Threshold Violation**: The transaction amount is above the average transaction amount for this customer, which may indicate a potential threshold violation.\n2. **Suspicious Pattern**: The transaction pattern is unusual for this customer, which may indicate a potential suspicious activity.\n\n**Escalation or Further Investigation:**\n\nThe transaction warrants further investigation and escalation to the relevant regulatory authorities to report the unusual transaction pattern and potential compliance risks.",
    "transaction_details": {
      "amount": 45000.0,
      "frequency30Day": 45,
      "customerAvgAmount": 18000.0,
      "customerTotalTransactions": 72,
      "geographicDistance": 1150.0,
      "cityDistance": 1400.0,
      "transactionType": "Cash Deposit",
      "unusualForCustomer": "Yes",
      "customerRiskProfile": "Medium",
      "transactionPurpose": "Loan Repayment",
      "historicalRiskScore": 73.0,
      "customerIndustry": "Finance",
      "originCountry": "India",
      "destinationCountry": "India",
      "originCity": "Mumbai",
      "destinationCity": "Delhi",
      "customerType": "Individual",
      "customer_id": "CUS456"
    },
    "timestamp": "2025-04-21T13:40:20.337598+00:00"
  },
  {
    "alert_type": "Transaction Anomaly",
    "severity": "MEDIUM",
    "action_recommendation": "**Transaction Overview:**\n\nThe transaction involves a cash deposit of INR 50,000.0 (approximately USD 690) from an individual customer (CUS5678) in Mumbai, India, to a recipient in Delhi, India. The customer has a medium risk profile, and this transaction is flagged as unusual for the customer. The transaction purpose is loan repayment, and the customer's average transaction amount is INR 20,000.0.\n\n**Relevance to AML/KYC Compliance:**\n\n1. **Customer Due Diligence (CDD):** The customer has a medium risk profile, which requires enhanced due diligence. However, the transaction purpose is loan repayment, which is a legitimate transaction.\n2. **Transaction Monitoring:** The transaction amount is above the average transaction amount for the customer, but it is still within the customer's usual transaction frequency.\n3. **Geographic Distance:** The transaction involves a geographic distance of 1150.0 km between the origin and destination, which may indicate a legitimate transaction.\n4. **Unusual Transaction Patterns:** The transaction frequency is 45 in 30 days, which is above the customer's average transaction frequency. However, it is still within the customer's usual transaction pattern.\n5. **Counterparty Risk:** The recipient's information is not provided, which increases the risk of the transaction.\n6. **Sanctions and PEP Screening:** The customer's origin and destination countries are India, and the customer is an individual, which reduces the risk of sanctions and PEP involvement.\n7. **Transaction Purpose:** The transaction purpose is loan repayment, which is a legitimate transaction.\n\n**Anomaly Detection Flags:**\n\n1. **High Transaction Frequency:** The transaction frequency is above the customer's average transaction frequency, which may indicate a legitimate but unusual transaction pattern.\n2. **Large Transaction Amount:** The transaction amount is above the customer's average transaction amount, which may indicate a legitimate but unusual transaction.\n\n**Recommendations for Risk Mitigation:**\n\n1. **Enhanced Due Diligence:** Perform enhanced due diligence on the customer to gather more information about their financial activities and sources of funds.\n2. **Transaction Monitoring:** Continue to monitor the customer's transactions to identify any unusual patterns or deviations from their usual transaction behavior.\n3. **Counterparty Risk Assessment:** Obtain more information about the recipient to assess the counterparty risk and ensure that the transaction is not associated with any high-risk activities.\n4. **SAR Filing:** File a Suspicious Activity Report (SAR) if any further investigation reveals suspicious activity or a potential violation of AML/KYC regulations.\n\n**Severity of Potential Violations:**\n\nThe severity of potential violations is classified as LOW. The transaction appears to be legitimate, but the unusual transaction frequency and amount require further investigation to ensure compliance with AML/KYC regulations.\n\n**Regulatory Concerns:**\n\n1. **Threshold Violation:** The transaction amount is above the customer's average transaction amount, which may indicate a potential threshold violation.\n2. **Suspicious Patterns:** The transaction frequency is above the customer's average transaction frequency, which may indicate a potential suspicious pattern.\n3. **High-Risk Counterparty:** The recipient's information is not provided, which increases the risk of the transaction.\n\n**Escalation or Further Investigation:**\n\nThe transaction warrants further investigation to ensure compliance with AML/KYC regulations. The customer's transactions should be monitored closely to identify any unusual patterns or deviations from their usual transaction behavior. If any further investigation reveals suspicious activity or a potential violation of AML/KYC regulations, a SAR should be filed.",
    "transaction_details": {
      "amount": 50000.0,
      "frequency30Day": 45,
      "customerAvgAmount": 20000.0,
      "customerTotalTransactions": 78,
      "geographicDistance": 1150.0,
      "cityDistance": 1400.0,
      "transactionType": "Cash Deposit",
      "unusualForCustomer": "No",
      "customerRiskProfile": "Medium",
      "transactionPurpose": "Loan Repayment",
      "historicalRiskScore": 74.0,
      "customerIndustry": "Finance",
      "originCountry": "India",
      "destinationCountry": "India",
      "originCity": "Mumbai",
      "destinationCity": "Delhi",
      "customerType": "Individual",
      "customer_id": "CUS5678"
    },
    "timestamp": "2025-04-29T12:01:54.482807+00:00"
  },
  {
    "alert_type": "Transaction Anomaly",
    "severity": "HIGH",
    "action_recommendation": "**Transaction Analysis for AML/KYC Compliance**\n\n**Overview of Transaction Fields and Relevance to AML/KYC Compliance:**\n\n1. **amount**: 50000.0 INR (Relevant: Large or unusual transaction)\n2. **frequency30Day**: 42 (Relevant: Potential pattern of frequent transactions)\n3. **customerAvgAmount**: 20000.0 INR (Relevant: Customer's average transaction amount, may indicate deviation from normal behavior)\n4. **customerTotalTransactions**: 60 (Relevant: Customer's total transaction history, may indicate suspicious activity)\n5. **geographicDistance**: 1140.0 km (Relevant: Distance between origin and destination cities, may indicate cross-border activity)\n6. **cityDistance**: 1400.0 km (Relevant: Distance between origin and destination cities, may indicate cross-border activity)\n7. **transactionType**: Cash Deposit (Relevant: Unusual or high-risk transaction type)\n8. **unusualForCustomer**: No (Relevant: Whether the transaction is unusual for the customer)\n9. **customerRiskProfile**: Medium (Relevant: Customer's risk profile, may indicate high-risk behavior)\n10. **transactionPurpose**: Loan Repayment (Relevant: Transaction purpose, may indicate unusual or suspicious activity)\n11. **historicalRiskScore**: 72.5 (Relevant: Customer's historical risk score, may indicate high-risk behavior)\n12. **customerIndustry**: Finance (Relevant: Customer's industry, may indicate high-risk activity)\n13. **originCountry**: India (Relevant: Origin country, may indicate domestic transaction)\n14. **destinationCountry**: India (Relevant: Destination country, may indicate domestic transaction)\n15. **originCity**: Delhi (Relevant: Origin city, may indicate geographic location)\n16. **destinationCity**: Mumbai (Relevant: Destination city, may indicate geographic location)\n17. **customerType**: Individual (Relevant: Customer type, may indicate personal account)\n18. **customer_id**: CUS3452 (Relevant: Customer ID, may indicate specific customer behavior)\n\n**Potential Compliance Risks:**\n\n1. **Large and unusual transaction**: The transaction amount (50000.0 INR) is significantly higher than the customer's average transaction amount (20000.0 INR), which may indicate unusual or suspicious activity.\n2. **Frequent transactions**: The customer has made 42 transactions in the last 30 days, which may indicate a pattern of frequent transactions and potential structuring or smurfing activities.\n3. **Medium-risk customer**: The customer's risk profile is classified as Medium, which may indicate a higher risk of money laundering or terrorist financing.\n4. **Loan repayment transaction**: The transaction purpose is Loan Repayment, which may indicate unusual or suspicious activity, as loan repayments are typically not cash deposits.\n\n**Anomaly Detection Flags:**\n\n1. **Large and unusual transaction**: The transaction amount is significantly higher than the customer's average transaction amount.\n2. **Frequent transactions**: The customer has made 42 transactions in the last 30 days, which may indicate a pattern of frequent transactions.\n3. **Medium-risk customer**: The customer's risk profile is classified as Medium, which may indicate a higher risk of money laundering or terrorist financing.\n\n**Recommendations for Risk Mitigation:**\n\n1. **Enhanced due diligence**: Conduct additional due diligence on the customer to verify their identity and assess their risk profile.\n2. **SAR filing**: File a Suspicious Activity Report (SAR) with the relevant regulatory authorities to report the unusual transaction.\n3. **Transaction monitoring**: Monitor the customer's future transactions to detect any potential suspicious activity.\n\n**Severity of Potential Violations:**\n\n1. **HIGH**: The transaction amount is significantly higher than the customer's average transaction amount, and the customer's risk profile is classified as Medium.\n2. **MEDIUM**: The customer has made 42 transactions in the last 30 days, which may indicate a pattern of frequent transactions.\n\n**Regulatory Concerns:**\n\n1. **Threshold violations**: The transaction amount exceeds the customer's average transaction amount, which may indicate a threshold violation.\n2. **Suspicious patterns**: The customer's transaction pattern may indicate suspicious activity, such as frequent transactions or large and unusual transactions.\n3. **High-risk customer**: The customer's risk profile is classified as Medium, which may indicate a higher risk of money laundering or terrorist financing.\n\n**Escalation or Further Investigation:**\n\nYes, the transaction warrants escalation or further investigation due to the potential compliance risks and anomaly detection flags.",
    "transaction_details": {
      "amount": 50000.0,
      "frequency30Day": 42,
      "customerAvgAmount": 20000.0,
      "customerTotalTransactions": 60,
      "geographicDistance": 1140.0,
      "cityDistance": 1400.0,
      "transactionType": "Cash Deposit",
      "unusualForCustomer": "No",
      "customerRiskProfile": "Medium",
      "transactionPurpose": "Loan Repayment",
      "historicalRiskScore": 72.5,
      "customerIndustry": "Finance",
      "originCountry": "India",
      "destinationCountry": "India",
      "originCity": "Delhi",
      "destinationCity": "Mumbai",
      "customerType": "Individual",
      "customer_id": "CUS3452"
    },
    "timestamp": "2025-05-20T14:54:47.306741+00:00"
  },
  {
    "alert_type": "Transaction Anomaly",
    "severity": "MEDIUM",
    "action_recommendation": "**Transaction Field Analysis and Relevance to AML/KYC Compliance**\n\n1. **amount**: INR 42,000.00 - This amount is relatively high, considering the customer's average transaction amount is INR 20,000.00. This may warrant further investigation.\n2. **frequency30Day**: 42 transactions in 30 days - This frequency is higher than expected, indicating a potential pattern of rapid movement of funds.\n3. **customerAvgAmount**: INR 20,000.00 - This average transaction amount is lower than the current transaction, suggesting that the customer may be trying to structure transactions to avoid reporting thresholds.\n4. **customerTotalTransactions**: 72 - This total transaction count is relatively high, indicating a high transaction volume for the customer.\n5. **geographicDistance**: 1100.0 km - The distance between the origin and destination cities is significant, which may indicate a potential cash transfer or structuring activity.\n6. **cityDistance**: 1400.0 km - The distance between the origin and destination cities is even greater than the geographic distance, suggesting that the transaction may be unrelated to the customer's business activities.\n7. **transactionType**: Cash Deposit - Cash deposits are high-risk transactions, as they can be used to launder money or finance illegal activities.\n8. **unusualForCustomer**: No - The transaction is not unusual for the customer, but this field may not be reliable, as it is based on the customer's historical behavior.\n9. **customerRiskProfile**: Medium - The customer's risk profile is medium, indicating that they may be a high-risk customer.\n10. **transactionPurpose**: Loan Repayment - The transaction purpose is legitimate, but it may be used as a cover for illegal activities.\n11. **historicalRiskScore**: 70.0 - The customer's historical risk score is relatively high, indicating that they may have engaged in suspicious activities in the past.\n12. **customerIndustry**: Finance - The customer is in the finance industry, which is a high-risk sector.\n13. **originCountry**: India - The origin country is India, which is a high-risk jurisdiction due to its reputation for money laundering and terrorist financing.\n14. **destinationCountry**: India - The destination country is also India, which may indicate an attempt to structure or launder money.\n15. **originCity**: Mumbai - Mumbai is a high-risk city due to its reputation for money laundering and terrorist financing.\n16. **destinationCity**: Delhi - Delhi is also a high-risk city, indicating that the transaction may be related to illegal activities.\n17. **customerType**: Individual - The customer is an individual, which is a high-risk type of customer due to their potential for money laundering and terrorist financing.\n18. **customer_id**: CUS8167 - The customer ID may be used to identify the customer and their transactions.\n\n**Potential Compliance Risks and Anomaly Detection Flags**\n\n1. **High-risk jurisdiction**: The transaction involves India, which is a high-risk jurisdiction.\n2. **Unusual transaction pattern**: The frequency and amount of the transaction are unusual for the customer.\n3. **Deviations from customer profile**: The transaction amount and frequency deviate from the customer's average transaction amount and frequency.\n4. **Potential structuring or layering**: The transaction may be used to structure or launder money.\n5. **High-risk industry**: The customer is in the finance industry, which is a high-risk sector.\n\n**Recommended Actions and Severity Classification**\n\n1. **Enhanced due diligence**: Conduct enhanced due diligence on the customer, including a review of their financial records and business activities.\n2. **SAR filing**: File a suspicious activity report (SAR) with the regulatory authorities due to the potential compliance risks identified.\n3. **Transaction monitoring**: Monitor the transaction for any further suspicious activity, including rapid movement of funds or transactions with no apparent economic or lawful purpose.\n4. **Customer risk rating**: Re-evaluate the customer's risk rating and consider updating it to a higher level based on the potential compliance risks identified.\n5. **Severity classification**: The severity of the potential violations is HIGH, due to the combination of high-risk jurisdiction, unusual transaction pattern, and deviations from customer profile.\n\n**Conclusion**\n\nThe transaction warrants further investigation and escalation to the relevant authorities due to the potential compliance risks identified. The recommended actions are designed to mitigate these risks and ensure AML/KYC compliance.",
    "transaction_details": {
      "amount": 42000.0,
      "frequency30Day": 42,
      "customerAvgAmount": 20000.0,
      "customerTotalTransactions": 72,
      "geographicDistance": 1100.0,
      "cityDistance": 1400.0,
      "transactionType": "Cash Deposit",
      "unusualForCustomer": "No",
      "customerRiskProfile": "Medium",
      "transactionPurpose": "Loan Repayment",
      "historicalRiskScore": 70.0,
      "customerIndustry": "Finance",
      "originCountry": "India",
      "destinationCountry": "India",
      "originCity": "Mumbai",
      "destinationCity": "Delhi",
      "customerType": "Individual",
      "customer_id": "CUS8167"
    },
    "timestamp": "2025-05-29T11:36:41.294101+00:00"
  }
]